ODTReader
