Metadata-Version: 1.1
Name: ODTReader
Version: 0.0.5
Summary: Lightweight python module to allow extracting text from OpenDocument (odt) files.
Home-page: https://github.com/KaneGalba/ODTReader/
Author: Kane Galba
Author-email: kane@galba.co
License: GPL
Download-URL: https://github.com/KaneGalba/ODTReader/archive/master.zip
Platform: any
